langchain_chroma/__init__.py
langchain_chroma/py.typed
langchain_chroma/vectorstores.py
gigachain_chroma-0.1.3.dist-info/LICENSE
gigachain_chroma-0.1.3.dist-info/METADATA
gigachain_chroma-0.1.3.dist-info/WHEEL
gigachain_chroma-0.1.3.dist-info/RECORD
