Metadata-Version: 2.1
Name: gigachain-chroma
Version: 0.1.3
Summary: An integration package connecting Chroma and LangChain
Home-page: https://github.com/ai-forever/gigachain
License: MIT
Requires-Python: >=3.8.1,<4
Classifier: License :: OSI Approved :: MIT License
Classifier: Programming Language :: Python :: 3
Classifier: Programming Language :: Python :: 3.9
Classifier: Programming Language :: Python :: 3.10
Classifier: Programming Language :: Python :: 3.11
Classifier: Programming Language :: Python :: 3.12
Requires-Dist: chromadb (>=0.4.0,<0.6.0,!=0.5.4,!=0.5.5)
Requires-Dist: fastapi (>=0.95.2,<1)
Requires-Dist: gigachain-core (>=0.1.40,<0.3)
Requires-Dist: numpy (>=1,<2) ; python_version < "3.12"
Requires-Dist: numpy (>=1.26.0,<2.0.0) ; python_version >= "3.12"
Project-URL: Repository, https://github.com/ai-forever/gigachain
Project-URL: Release Notes, https://github.com/ai-forever/gigachain/releases?q=tag%3A%22gigachain-chroma%3D%3D0%22&expanded=true
Project-URL: Source Code, https://github.com/ai-forever/gigachain/tree/master/libs/partners/chroma
